marketing_metrics/__init__.py
marketing_metrics/example.py
marketing_metrics-0.0.1.dist-info/METADATA
marketing_metrics-0.0.1.dist-info/WHEEL
marketing_metrics-0.0.1.dist-info/licenses/LICENSE
marketing_metrics-0.0.1.dist-info/RECORD
