Metadata-Version: 2.1
Name: marketing-metrics
Version: 0.0.1
Summary: Calculate Marketing Metrics
Project-URL: homepage, https://mohsenebrahimyir.github.io/marketing-metrics/
Project-URL: repository, https://github.com/mohsenebrahimyir/marketing-metrics.git
Author-email: Mohsen Ebrahimi <mohsenebrahimy.ir@gmail.com>
License: MIT License
Classifier: License :: OSI Approved :: MIT License
Classifier: Operating System :: OS Independent
Classifier: Programming Language :: Python :: 3
Requires-Python: >=3.8
